{"assets":{"14D9254E30F70F448172663C46449B01":{"type":"texture","index":0,"url":{"native":"assets\/1DACB8A9-F757-4C30-8FA2-C82B714BCE98.pdf"},"width":1920,"height":1080},"5BA6DF7ACEF516F7DAB78587CF30CE20":{"type":"texture","index":1,"url":{"native":"assets\/1DACB8A9-F757-4C30-8FA2-C82B714BCE98.pdf"},"width":1920,"height":1080}},"events":[{"effects":[{"beginTime":0,"baseLayer":{"animations":[],"initialState":{"affineTransform":[1,0,0,1,0,0],"masksToBounds":false,"rotation":0,"scale":1,"position":{"pointX":960,"pointY":540},"width":1920,"sublayerTransform":[1,0,0,0,0,1,0,0,0,0,1,0,0,0,0,1],"contentsRect":{"y":0,"x":0,"width":1,"height":1},"opacity":1,"edgeAntialiasingMask":251658240,"height":1080,"hidden":false,"anchorPoint":{"pointX":0.5,"pointY":0.5}},"objectID":"0","layers":[{"animations":[],"initialState":{"affineTransform":[1,0,0,1,0,0],"masksToBounds":false,"rotation":0,"scale":1,"position":{"pointX":960,"pointY":540},"width":1920,"sublayerTransform":[1,0,0,0,0,1,0,0,0,0,1,-0.00035007912466775983,0,0,0,1],"contentsRect":{"y":0,"x":0,"width":1,"height":1},"opacity":1,"edgeAntialiasingMask":251658240,"height":1080,"hidden":false,"anchorPoint":{"pointX":0.5,"pointY":0.5}},"layers":[{"animations":[],"layers":[],"texturedRectangle":{"isBackgroundTexture":false,"singleTextureOpacity":1,"textureType":0,"textBaseline":0,"textXHeight":0,"isVerticalText":false},"initialState":{"affineTransform":[1,0,0,1,0,0],"masksToBounds":false,"rotation":0,"scale":1,"position":{"pointX":960,"pointY":540},"width":1920,"sublayerTransform":[1,0,0,0,0,1,0,0,0,0,1,0,0,0,0,1],"contentsRect":{"y":0,"x":0,"width":1,"height":1},"opacity":1,"edgeAntialiasingMask":0,"height":1080,"hidden":false,"anchorPoint":{"pointX":0.5,"pointY":0.5}},"texture":"5BA6DF7ACEF516F7DAB78587CF30CE20"},{"animations":[{"additive":false,"timeOffset":0,"beginTime":0,"from":{"scalar":false},"repeatCount":0,"fillMode":"both","duration":0.01,"autoreverses":false,"property":"hidden","to":{"scalar":true},"removedOnCompletion":false}],"layers":[],"texturedRectangle":{"isBackgroundTexture":false,"singleTextureOpacity":1,"textureType":0,"textBaseline":0,"textXHeight":0,"isVerticalText":false},"initialState":{"affineTransform":[1,0,0,1,0,0],"masksToBounds":false,"rotation":0,"scale":1,"position":{"pointX":960,"pointY":540},"width":1920,"sublayerTransform":[1,0,0,0,0,1,0,0,0,0,1,0,0,0,0,1],"contentsRect":{"y":0,"x":0,"width":1,"height":1},"opacity":1,"edgeAntialiasingMask":0,"height":1080,"hidden":false,"anchorPoint":{"pointX":0.5,"pointY":0.5}},"texture":"14D9254E30F70F448172663C46449B01"}]}]},"effects":[],"duration":0.01,"type":"transition","attributes":{"direction":0},"name":"none","objectID":"0"}],"automaticPlay":false,"hyperlinks":[],"accessibility":[{"text":"비트코인이 블록체인을 통해 해결한 문제","targetRectangle":{"y":738.29125642776489,"x":109.31503295898438,"width":759.21600000000012,"height":59.832158088684082}},{"text":"전자 화폐로서 동작하기 위해 필요한 요소","targetRectangle":{"y":137.3114013671875,"x":94.800994873046875,"width":1126.6500000000001,"height":88.77988874912262}},{"text":"소유 할 수 있어야 한다.","targetRectangle":{"y":338.52792358398438,"x":147,"width":440.39999999999986,"height":59.832158088684082}},{"text":"안전하게 거래 할 수 있어야 한다.","targetRectangle":{"y":393.72085857791524,"x":147,"width":619.82399999999996,"height":104.83215808868408}},{"text":"마이너스 잔액이 불가해야 한다. (초과 지출 문제)","targetRectangle":{"y":493.9137935718461,"x":147,"width":907.15200000000004,"height":104.83215808868408}},{"text":"거래 내역 복사가 불가해야 한다.(이중 지불 문제)","targetRectangle":{"y":594.10672856577696,"x":147,"width":907.15200000000004,"height":105.59192371368408}},{"text":"작업 증명(PoW)","targetRectangle":{"y":570.28491139411926,"x":1401.8468437194824,"width":397.048,"height":77.658204197883606}},{"text":"디지털 서명","targetRectangle":{"y":835.23146867752075,"x":240.3843994140625,"width":487.91800000000001,"height":133.25434911251068}},{"text":"해시 함수","targetRectangle":{"y":835.23146867752075,"x":1241.48583984375,"width":396.22800000000007,"height":133.25434911251068}},{"text":"작업 증명","targetRectangle":{"y":835.23146867752075,"x":786.7801513671875,"width":396.22800000000007,"height":133.25434911251068}},{"text":"원장(Ledger), 디지털 서명","targetRectangle":{"y":371.78870391845703,"x":1164.8943338394165,"width":653.29399999999987,"height":77.658204197883606}},{"text":"How?","targetRectangle":{"y":649.51768779754639,"x":1202.0408935546875,"width":276.65999999999985,"height":124.03201293945312}}],"baseLayer":{"animations":[],"initialState":{"affineTransform":[1,0,0,1,0,0],"masksToBounds":false,"rotation":0,"scale":1,"position":{"pointX":960,"pointY":540},"width":1920,"sublayerTransform":[1,0,0,0,0,1,0,0,0,0,1,0,0,0,0,1],"contentsRect":{"y":0,"x":0,"width":1,"height":1},"opacity":1,"edgeAntialiasingMask":251658240,"height":1080,"hidden":false,"anchorPoint":{"pointX":0.5,"pointY":0.5}},"objectID":"0","layers":[{"animations":[],"initialState":{"affineTransform":[1,0,0,1,0,0],"masksToBounds":false,"rotation":0,"scale":1,"position":{"pointX":960,"pointY":540},"width":1920,"sublayerTransform":[1,0,0,0,0,1,0,0,0,0,1,-0.00035007912466775983,0,0,0,1],"contentsRect":{"y":0,"x":0,"width":1,"height":1},"opacity":1,"edgeAntialiasingMask":251658240,"height":1080,"hidden":false,"anchorPoint":{"pointX":0.5,"pointY":0.5}},"layers":[{"animations":[],"layers":[],"texturedRectangle":{"isBackgroundTexture":false,"singleTextureOpacity":1,"textureType":0,"textBaseline":0,"textXHeight":0,"isVerticalText":false},"initialState":{"affineTransform":[1,0,0,1,0,0],"masksToBounds":false,"rotation":0,"scale":1,"position":{"pointX":960,"pointY":540},"width":1920,"sublayerTransform":[1,0,0,0,0,1,0,0,0,0,1,0,0,0,0,1],"contentsRect":{"y":0,"x":0,"width":1,"height":1},"opacity":1,"edgeAntialiasingMask":0,"height":1080,"hidden":false,"anchorPoint":{"pointX":0.5,"pointY":0.5}},"texture":"14D9254E30F70F448172663C46449B01"}]}]}}]}